beamprofiler/__init__.py
beamprofiler/beam.py
beamprofiler/iso/__init__.py
beamprofiler/iso/characterizing_parameters.py
beamprofiler/iso/measured_quantities.py
beamprofiler/niso/__init__.py
beamprofiler/niso/characterizing_parameters.py
beamprofiler/utils/__init__.py
beamprofiler/utils/data_processing.py
beamprofiler/utils/plot.py
beamprofiler/utils/report.py
beamprofiler-1.2.0.dist-info/AUTHORS.rst
beamprofiler-1.2.0.dist-info/LICENSE
beamprofiler-1.2.0.dist-info/METADATA
beamprofiler-1.2.0.dist-info/WHEEL
beamprofiler-1.2.0.dist-info/top_level.txt
beamprofiler-1.2.0.dist-info/RECORD
