Metadata-Version: 2.1
Name: beamprofiler
Version: 1.2.0
Summary: BeamProfiler is a Python package for laser beam analysis and characterization according to ISO 13694, ISO 11145, and other non-ISO definitions commonly used in the industry.
Home-page: https://github.com/wagnojunior/beamprofiler
Author: Wagno Alves Braganca Jr.
Author-email: wagnojunior@gmail.com
License: GNU General Public License v3
Keywords: beamprofiler
Classifier: Development Status :: 2 - Pre-Alpha
Classifier: Intended Audience :: Developers
Classifier: License :: OSI Approved :: GNU General Public License v3 (GPLv3)
Classifier: Natural Language :: English
Classifier: Programming Language :: Python :: 3
Classifier: Programming Language :: Python :: 3.6
Classifier: Programming Language :: Python :: 3.7
Classifier: Programming Language :: Python :: 3.8
Requires-Python: >=3.6
License-File: LICENSE
License-File: AUTHORS.rst
Requires-Dist: cycler
Requires-Dist: fonttools
Requires-Dist: joblib
Requires-Dist: kiwisolver
Requires-Dist: matplotlib
Requires-Dist: numpy
Requires-Dist: packaging
Requires-Dist: pandas
Requires-Dist: pillow
Requires-Dist: pyparsing
Requires-Dist: python-dateutil
Requires-Dist: pytz
Requires-Dist: scikit-learn
Requires-Dist: scipy
Requires-Dist: six
Requires-Dist: threadpoolctl
Requires-Dist: xlsxwriter
